fablegen/__init__.py
fablegen/include/fablegen.cpython-311-darwin.so
fablegen-0.0.1.dist-info/LICENSE
fablegen-0.0.1.dist-info/METADATA
fablegen-0.0.1.dist-info/WHEEL
fablegen-0.0.1.dist-info/top_level.txt
fablegen-0.0.1.dist-info/RECORD
