Metadata-Version: 2.1
Name: fablegen
Version: 0.0.1
Summary: README.md
Author-email: Jack Bonatakis <jackbonataki@gmail.com>
License-File: LICENSE
Provides-Extra: dev
Requires-Dist: python-dotenv ; extra == 'dev'
Requires-Dist: pytest ; extra == 'dev'
Requires-Dist: ruff ; extra == 'dev'
